[
    {
        "編號": "1",
        "屬性": "私立",
        "機構名稱": "財團法人臺灣省私立永信社會福利基金會附設臺中市私立松柏園老人養護中心",
        "負責人": "李敏雄",
        "區域別": "大甲區",
        "地址": "437臺中市大甲區頂店里成功路319號",
        "電話": "04-26760180",
        "收容對象": "養護",
        "核定收容人數": "161(含插2管57床)",
        "立案日期": "90.11",
        "Latitude": "24.3601194",
        "Longitude": "120.6481"
    },
    {
        "編號": "2",
        "屬性": "私立",
        "機構名稱": "臺中市私立大甲老人養護中心",
        "負責人": "潘海濤",
        "區域別": "大甲區",
        "地址": "437臺中市大甲區順天里五福街59、61號1樓~3樓",
        "電話": "04-26865058",
        "收容對象": "養護",
        "核定收容人數": "22(含插2管11床)",
        "立案日期": "91.02",
        "Latitude": "24.3474361",
        "Longitude": "120.6200044"
    },
    {
        "編號": "3",
        "屬性": "私立",
        "機構名稱": "臺中市私立永和老人長期照顧中心(養護型)",
        "負責人": "林富美",
        "區域別": "大甲區",
        "地址": "437臺中市大甲區文武里育英路128號",
        "電話": "04-26870788",
        "收容對象": "養護",
        "核定收容人數": "48(含插2管24床)",
        "立案日期": "98.02",
        "Latitude": "24.3525973",
        "Longitude": "120.6245685"
    },
    {
        "編號": "4",
        "屬性": "私立",
        "機構名稱": "臺中市私立大愛老人養護中心",
        "負責人": "陳慧英",
        "區域別": "大里區",
        "地址": "412臺中市大里區勝利二路60號",
        "電話": "04-24854188",
        "收容對象": "養護",
        "核定收容人數": "45",
        "立案日期": "88.11",
        "Latitude": "24.100687",
        "Longitude": "120.686716"
    },
    {
        "編號": "5",
        "屬性": "私立",
        "機構名稱": "臺中市私立毓祥老人養護中心",
        "負責人": "蕭陳淑貞",
        "區域別": "大里區",
        "地址": "412臺中市大里區大元里中興路二段73號",
        "電話": "04-24831380",
        "收容對象": "養護",
        "核定收容人數": "33(含插2管16床)",
        "立案日期": "90.03",
        "Latitude": "24.0976449",
        "Longitude": "120.686651"
    },
    {
        "編號": "6",
        "屬性": "私立",
        "機構名稱": "臺中市私立清心老人養護中心",
        "負責人": "柯文華",
        "區域別": "大里區",
        "地址": "412臺中市大里區大元里內元路158號",
        "電話": "04-24864567",
        "收容對象": "養護",
        "核定收容人數": "49(含插2管15床)",
        "立案日期": "90.05",
        "Latitude": "24.0986155",
        "Longitude": "120.689954"
    },
    {
        "編號": "7",
        "屬性": "私立",
        "機構名稱": "台中市私立全家老人養護中心",
        "負責人": "廖明琳",
        "區域別": "大里區",
        "地址": "412臺中市大里區大元里東里路77號1、2樓",
        "電話": "04-24180505",
        "收容對象": "養護",
        "核定收容人數": "49(含插2管24床)",
        "立案日期": "96.01",
        "Latitude": "24.0957549",
        "Longitude": "120.6796205"
    },
    {
        "編號": "8",
        "屬性": "私立",
        "機構名稱": "財團法人台灣省私立菩提仁愛之家",
        "負責人": "簡金武",
        "區域別": "大里區",
        "地址": "臺中市大里區西榮里1鄰中興路2段619號",
        "電話": "04-24837148",
        "收容對象": "養護",
        "核定收容人數": "297(含插2管56床)",
        "立案日期": "53.01",
        "Latitude": "24.1151615",
        "Longitude": "120.6895075"
    },
    {
        "編號": "9",
        "屬性": "私立",
        "機構名稱": "臺中市私立健德老人養護中心",
        "負責人": "童鄭寶月",
        "區域別": "大雅區",
        "地址": "428臺中市大雅區六寶里光復路2-5號",
        "電話": "04-25604290",
        "收容對象": "長照",
        "核定收容人數": "6",
        "立案日期": "95.04",
        "Latitude": "24.2349438",
        "Longitude": "120.6282659"
    },
    {
        "編號": "9",
        "屬性": "私立",
        "機構名稱": "臺中市私立健德老人養護中心",
        "負責人": "童鄭寶月",
        "區域別": "大雅區",
        "地址": "428臺中市大雅區六寶里光復路2-5號",
        "電話": "04-25604290",
        "收容對象": "養護",
        "核定收容人數": "43(含插2管10床)",
        "立案日期": "95.04",
        "Latitude": "24.2349438",
        "Longitude": "120.6282659"
    },
    {
        "編號": "10",
        "屬性": "私立",
        "機構名稱": "台中市私立溫興長期照顧中心(養護型)",
        "負責人": "賴興建",
        "區域別": "中區",
        "地址": "400中市中區雙十路一段19巷6號",
        "電話": "04-22230938",
        "收容對象": "養護",
        "核定收容人數": "15(含插2管7床)",
        "立案日期": "102.03",
        "Latitude": "24.141011",
        "Longitude": "120.6850447"
    },
    {
        "編號": "11",
        "屬性": "私立",
        "機構名稱": "台中市私立麗安老人長期照顧中心(養護型)",
        "負責人": "張軒維",
        "區域別": "中區",
        "地址": "400臺中市中區成功路341號3、4樓",
        "電話": "04-22250345",
        "收容對象": "長照",
        "核定收容人數": "16",
        "立案日期": "103.3",
        "Latitude": "24.1452029",
        "Longitude": "120.6777284"
    },
    {
        "編號": "11",
        "屬性": "私立",
        "機構名稱": "台中市私立麗安老人長期照顧中心(養護型)",
        "負責人": "張軒維",
        "區域別": "中區",
        "地址": "400臺中市中區成功路341號3、4樓",
        "電話": "04-22250345",
        "收容對象": "養護",
        "核定收容人數": "32(含插2管15床)",
        "立案日期": "103.3",
        "Latitude": "24.1452029",
        "Longitude": "120.6777284"
    },
    {
        "編號": "12",
        "屬性": "公立",
        "機構名稱": "臺中市立仁愛之家",
        "負責人": "蘇淑貞",
        "區域別": "北屯區",
        "地址": "406臺中市北屯區軍功里軍功路二段490號",
        "電話": "04-22392074(蔡主任*1200)",
        "收容對象": "安養",
        "核定收容人數": "100",
        "立案日期": "62.01",
        "Latitude": "24.1840727",
        "Longitude": "120.7200816"
    },
    {
        "編號": "12",
        "屬性": "公立",
        "機構名稱": "臺中市立仁愛之家",
        "負責人": "蘇淑貞",
        "區域別": "北屯區",
        "地址": "406臺中市北屯區軍功里軍功路二段490號",
        "電話": "04-22392074(蔡主任*1200)",
        "收容對象": "養護",
        "核定收容人數": "400",
        "立案日期": "62.01",
        "Latitude": "24.1840727",
        "Longitude": "120.7200816"
    },
    {
        "編號": "13",
        "屬性": "私立",
        "機構名稱": "台中市私立真善美老人養護中心",
        "負責人": "陳志銘",
        "區域別": "北屯區",
        "地址": "406臺中市北屯區三和里東山路一段50巷63號",
        "電話": "04-24363201 04-24369228",
        "收容對象": "養護",
        "核定收容人數": "29(含插2管14床)",
        "立案日期": "91.05",
        "Latitude": "24.1669117",
        "Longitude": "120.7020989"
    },
    {
        "編號": "14",
        "屬性": "私立",
        "機構名稱": "台中市私立惠恩老人養護中心",
        "負責人": "張惠珍",
        "區域別": "北屯區",
        "地址": "406臺中市北屯區仁美里崇德路三段746巷90號",
        "電話": "04-24223627",
        "收容對象": "養護",
        "核定收容人數": "45(含插2管21床)",
        "立案日期": "89.07",
        "Latitude": "24.204792",
        "Longitude": "120.6878796"
    },
    {
        "編號": "15",
        "屬性": "私立",
        "機構名稱": "臺中市私立同心居老人養護中心",
        "負責人": "陳龍飛",
        "區域別": "北屯區",
        "地址": "406臺中市北屯區仁和里崇德十路二段266號",
        "電話": "04-24225880 04-24225958",
        "收容對象": "養護",
        "核定收容人數": "49(含插2管15床)",
        "立案日期": "92.07",
        "Latitude": "24.1910731",
        "Longitude": "120.6780336"
    },
    {
        "編號": "16",
        "屬性": "私立",
        "機構名稱": "臺中市私立長生老人養護中心",
        "負責人": "張良卿",
        "區域別": "北屯區",
        "地址": "406臺中市北屯區仁美里崇德路三段942號",
        "電話": "04-24226226",
        "收容對象": "養護",
        "核定收容人數": "49(含插2管20床)",
        "立案日期": "87.07",
        "Latitude": "24.2034251",
        "Longitude": "120.6868352"
    },
    {
        "編號": "17",
        "屬性": "私立",
        "機構名稱": "台中市私立大德老人養護中心",
        "負責人": "吳錦煽",
        "區域別": "北屯區",
        "地址": "406臺中市北屯區忠平里陳平一街36巷30號、32號",
        "電話": "04-22930666 04-22989030",
        "收容對象": "養護",
        "核定收容人數": "36(含插2管10床)",
        "立案日期": "91.03",
        "Latitude": "24.184269",
        "Longitude": "120.6687295"
    },
    {
        "編號": "18",
        "屬性": "私立",
        "機構名稱": "臺中市私立欣德老人長期照顧中心(養護型)",
        "負責人": "吳錦煽",
        "區域別": "北屯區",
        "地址": "406臺中市北屯區平德里青島路三段13號",
        "電話": "04-22316611",
        "收容對象": "長照",
        "核定收容人數": "14",
        "立案日期": "97.02",
        "Latitude": "24.168854",
        "Longitude": "120.679426"
    },
    {
        "編號": "18",
        "屬性": "私立",
        "機構名稱": "臺中市私立欣德老人長期照顧中心(養護型)",
        "負責人": "吳錦煽",
        "區域別": "北屯區",
        "地址": "406臺中市北屯區平德里青島路三段13號",
        "電話": "04-22316611",
        "收容對象": "養護",
        "核定收容人數": "29(含插2管14床)",
        "立案日期": "97.02",
        "Latitude": "24.168854",
        "Longitude": "120.679426"
    },
    {
        "編號": "19",
        "屬性": "私立",
        "機構名稱": "台中市私立永春老人長期照顧中心(養護型)",
        "負責人": "古錦瑜",
        "區域別": "北屯區",
        "地址": "406臺中市北屯區和平里東山路一段308號2樓",
        "電話": "04-24368956",
        "收容對象": "養護",
        "核定收容人數": "46(含插2管20床)",
        "立案日期": "99.07",
        "Latitude": "24.1758344",
        "Longitude": "120.7211634"
    },
    {
        "編號": "20",
        "屬性": "私立",
        "機構名稱": "台中市私立永安老人長期照顧中心(養護型)",
        "負責人": "賴玉娟",
        "區域別": "北屯區",
        "地址": "406臺中市北屯區北平路四段199號",
        "電話": "04-22389266",
        "收容對象": "養護",
        "核定收容人數": "47(含插2管23床)",
        "立案日期": "102.1",
        "Latitude": "24.1698195",
        "Longitude": "120.6966559"
    },
    {
        "編號": "21",
        "屬性": "私立",
        "機構名稱": "台中市私立嘉民老人長期照顧中心(養護型)",
        "負責人": "張美紅",
        "區域別": "北屯區",
        "地址": "406臺中市北屯區環中東路二段255號3樓",
        "電話": "04-24370892",
        "收容對象": "養護",
        "核定收容人數": "48(含插2管24床)",
        "立案日期": "103.01",
        "Latitude": "24.177055",
        "Longitude": "120.7211977"
    },
    {
        "編號": "22",
        "屬性": "私立",
        "機構名稱": "台中市私立福欣老人長期照顧中心(養護型)",
        "負責人": "吳伊娟",
        "區域別": "北屯區",
        "地址": "406臺中市北屯區東山路一段308號5樓",
        "電話": "04-24376502",
        "收容對象": "養護",
        "核定收容人數": "46床(含插2管23床)",
        "立案日期": "103.8",
        "Latitude": "24.1758344",
        "Longitude": "120.7211634"
    },
    {
        "編號": "23",
        "屬性": "私立",
        "機構名稱": "財團法人臺中市私立長生老人長期照護中心",
        "負責人": "李從華",
        "區域別": "北區",
        "地址": "404臺中市北區錦祥里北屯路26號9、10、12樓(不含12樓之9及12樓之10)",
        "電話": "04-22302033",
        "收容對象": "長照",
        "核定收容人數": "91",
        "立案日期": "88.11",
        "Latitude": "24.1616147",
        "Longitude": "120.6926564"
    },
    {
        "編號": "24",
        "屬性": "私立",
        "機構名稱": "財團法人台中市順天宮輔順將軍廟附設私立輔順仁愛之家",
        "負責人": "陳英郎",
        "區域別": "北區",
        "地址": "404臺中市北區賴村里德化街362號",
        "電話": "04-22030602(李主任*100)",
        "收容對象": "安養",
        "核定收容人數": "128",
        "立案日期": "82.1",
        "Latitude": "24.1617538",
        "Longitude": "120.6801987"
    },
    {
        "編號": "24",
        "屬性": "私立",
        "機構名稱": "財團法人台中市順天宮輔順將軍廟附設私立輔順仁愛之家",
        "負責人": "陳英郎",
        "區域別": "北區",
        "地址": "404臺中市北區賴村里德化街362號",
        "電話": "04-22030602(李主任*100)",
        "收容對象": "養護",
        "核定收容人數": "42(含插2管20床)",
        "立案日期": "82.1",
        "Latitude": "24.1617538",
        "Longitude": "120.6801987"
    },
    {
        "編號": "25",
        "屬性": "私立",
        "機構名稱": "台中市私立永和老人養護中心",
        "負責人": "陳其宏",
        "區域別": "北區",
        "地址": "404臺中市北區淡溝里西屯路一段250巷1號",
        "電話": "04-22030609",
        "收容對象": "養護",
        "核定收容人數": "49(含插2管24床)",
        "立案日期": "90.07",
        "Latitude": "24.1561089",
        "Longitude": "120.668949"
    },
    {
        "編號": "26",
        "屬性": "私立",
        "機構名稱": "台中市私立信望愛老人養護中心",
        "負責人": "王興源",
        "區域別": "北區",
        "地址": "404臺中市北區育德里美德街211號2樓~6樓",
        "電話": "04-22031097 04-22057036",
        "收容對象": "養護",
        "核定收容人數": "49(含插2管24床)",
        "立案日期": "91.03",
        "Latitude": "24.1581079",
        "Longitude": "120.6790422"
    },
    {
        "編號": "27",
        "屬性": "私立",
        "機構名稱": "台中市私立慈恩老人養護中心",
        "負責人": "黃麗美",
        "區域別": "北區",
        "地址": "404臺中市北區賴村里健行路518巷15弄2號",
        "電話": "04-22039778",
        "收容對象": "養護",
        "核定收容人數": "48(含插2管10床)",
        "立案日期": "91.06",
        "Latitude": "24.1611297",
        "Longitude": "120.6791177"
    },
    {
        "編號": "28",
        "屬性": "私立",
        "機構名稱": "財團法人臺中市私立廣達社會福利慈善事業基金會附設臺中市私立廣達老人長期照顧中心(養護型)",
        "負責人": "陳瑞祥",
        "區域別": "外埔區",
        "地址": "438臺中市外埔區月眉西路398巷100號",
        "電話": "04-26836161",
        "收容對象": "養護",
        "核定收容人數": "200(含插2管75床)",
        "立案日期": "94.12",
        "Latitude": "24.3376154",
        "Longitude": "120.67262"
    },
    {
        "編號": "29",
        "屬性": "私立",
        "機構名稱": "臺中市私立常春老人養護中心",
        "負責人": "蔡瑞玉",
        "區域別": "外埔區",
        "地址": "438臺中市外埔區三坎里三坎路72-3號",
        "電話": "04-26839990",
        "收容對象": "養護　",
        "核定收容人數": "45(含插2管15床)",
        "立案日期": "91.1",
        "Latitude": "24.3192317",
        "Longitude": "120.6382919"
    },
    {
        "編號": "30",
        "屬性": "私立",
        "機構名稱": "臺中市私立安宜田園老人長期照顧中心(養護型)",
        "負責人": "施品華",
        "區域別": "外埔區",
        "地址": "438臺中市外埔區鐵山里長生路425號",
        "電話": "04-26838781",
        "收容對象": "養護",
        "核定收容人數": "48(含插2管17床)",
        "立案日期": "98.03",
        "Latitude": "24.3469914",
        "Longitude": "120.6544346"
    },
    {
        "編號": "31",
        "屬性": "私立",
        "機構名稱": "臺中市私立桃太郎老人養護中心",
        "負責人": "張邁轟",
        "區域別": "后里區",
        "地址": "421臺中市后里區墩南里南村路333巷42-36號3、4樓",
        "電話": "04-25561811",
        "收容對象": "養護",
        "核定收容人數": "46(含插2管23床)",
        "立案日期": "88.06",
        "Latitude": "24.2928202",
        "Longitude": "120.7118647"
    },
    {
        "編號": "32",
        "屬性": "私立",
        "機構名稱": "台中市私立杏林老人長期照顧中心(養護型)",
        "負責人": "黃信堯",
        "區域別": "西屯區",
        "地址": "407臺中市西屯區福雅里西屯路三段153-5號3樓~6樓",
        "電話": "04-24618119",
        "收容對象": "養護",
        "核定收容人數": "49(含插2管24床)",
        "立案日期": "89.01.26",
        "Latitude": "24.186485",
        "Longitude": "120.621404"
    },
    {
        "編號": "33",
        "屬性": "私立",
        "機構名稱": "台中市私立玫園老人養護中心",
        "負責人": "沈民慈",
        "區域別": "西屯區",
        "地址": "407臺中市西屯區林厝里福雅路465號",
        "電話": "04-24623902 04-24626799",
        "收容對象": "養護",
        "核定收容人數": "49(含插2管12床)",
        "立案日期": "92.12",
        "Latitude": "24.1974664",
        "Longitude": "120.6252976"
    },
    {
        "編號": "34",
        "屬性": "私立",
        "機構名稱": "臺中市私立長青老人養護中心",
        "負責人": "賴景明",
        "區域別": "西屯區",
        "地址": "407臺中市西屯區何南里大墩20街116號、118號1樓",
        "電話": "04-23107959",
        "收容對象": "養護",
        "核定收容人數": "47(含插2管23床)",
        "立案日期": "90.12",
        "Latitude": "24.158529",
        "Longitude": "120.651842"
    },
    {
        "編號": "35",
        "屬性": "私立",
        "機構名稱": "臺中市私立安健老人養護中心",
        "負責人": "童耀洲",
        "區域別": "西屯區",
        "地址": "407臺中市西屯區何明里太原路一段25號",
        "電話": "04-23119033",
        "收容對象": "養護",
        "核定收容人數": "49(含插2管22床)",
        "立案日期": "92.02",
        "Latitude": "24.1591186",
        "Longitude": "120.6583061"
    },
    {
        "編號": "36",
        "屬性": "私立",
        "機構名稱": "台中市私立善心園老人長期照顧中心(養護型)",
        "負責人": "陳峨梅",
        "區域別": "西屯區",
        "地址": "407臺中市西屯區福雅路550號",
        "電話": "04-24635886",
        "收容對象": "養護",
        "核定收容人數": "49(含插2管24床)",
        "立案日期": "104.08",
        "Latitude": "24.199788",
        "Longitude": "120.626734"
    },
    {
        "編號": "37",
        "屬性": "私立",
        "機構名稱": "臺中市私立福祿貝老老人養護中心",
        "負責人": "林威特",
        "區域別": "西區",
        "地址": "403臺中市西區後龍里梅川東路二段11號2~4樓",
        "電話": "04-22026788",
        "收容對象": "養護",
        "核定收容人數": "46(含插2管23床)",
        "立案日期": "87.07",
        "Latitude": "24.1503156",
        "Longitude": "120.6718909"
    },
    {
        "編號": "38",
        "屬性": "私立",
        "機構名稱": "台中市私立貝思特老人長期照顧中心(養護型)",
        "負責人": "林威特",
        "區域別": "西區",
        "地址": "403臺中市西區後龍里梅川東路二段11號5~6樓",
        "電話": "04-22026788",
        "收容對象": "長照",
        "核定收容人數": "13",
        "立案日期": "98.1",
        "Latitude": "24.1503156",
        "Longitude": "120.6718909"
    },
    {
        "編號": "38",
        "屬性": "私立",
        "機構名稱": "台中市私立貝思特老人長期照顧中心(養護型)",
        "負責人": "林威特",
        "區域別": "西區",
        "地址": "403臺中市西區後龍里梅川東路二段11號5~6樓",
        "電話": "04-22026788",
        "收容對象": "養護",
        "核定收容人數": "13(含插2管6床)",
        "立案日期": "98.1",
        "Latitude": "24.1503156",
        "Longitude": "120.6718909"
    },
    {
        "編號": "39",
        "屬性": "私立",
        "機構名稱": "台中市私立大墩老人養護中心",
        "負責人": "林秀蜜",
        "區域別": "西區",
        "地址": "403臺中市西區公正里向上路一段451號3~6樓",
        "電話": "04-24735983 04-24716768",
        "收容對象": "養護",
        "核定收容人數": "48(含插管15床)",
        "立案日期": "90.02",
        "Latitude": "24.1467212",
        "Longitude": "120.6538528"
    },
    {
        "編號": "40",
        "屬性": "私立",
        "機構名稱": "台中市私立長庚老人養護中心",
        "負責人": "黃金梅",
        "區域別": "西區",
        "地址": "403臺中市西區忠誠里精誠路72號3、4樓",
        "電話": "04-23103586",
        "收容對象": "養護",
        "核定收容人數": "40(含插2管20床)",
        "立案日期": "91.01",
        "Latitude": "24.1567032",
        "Longitude": "120.6570376"
    },
    {
        "編號": "41",
        "屬性": "私立",
        "機構名稱": "臺中市私立皇家老人養護中心",
        "負責人": "吳  心",
        "區域別": "沙鹿區",
        "地址": "433臺中市沙鹿區埔子里正義路97巷30號",
        "電話": "04-26336666",
        "收容對象": "養護",
        "核定收容人數": "40(含插2管20床)",
        "立案日期": "92.12",
        "Latitude": "24.2067175",
        "Longitude": "120.5704747"
    },
    {
        "編號": "42",
        "屬性": "私立",
        "機構名稱": "臺中市私立康祥老人長期照顧中心(養護型)",
        "負責人": "張淑貞",
        "區域別": "沙鹿區",
        "地址": "433臺中市沙鹿區三鹿里保成六街90號",
        "電話": "04-26367669",
        "收容對象": "養護",
        "核定收容人數": "32(含插2管10床)",
        "立案日期": "98.03",
        "Latitude": "24.2114938",
        "Longitude": "120.562586"
    },
    {
        "編號": "43",
        "屬性": "私立",
        "機構名稱": "臺中市私立惠群老人長期照顧中心(養護型)",
        "負責人": "劉桂芳",
        "區域別": "東區",
        "地址": "401臺中市東區干城里自由路三段276號5樓",
        "電話": "04-22130557",
        "收容對象": "養護",
        "核定收容人數": "47(含插2管23床)",
        "立案日期": "105.06.03",
        "Latitude": "24.1426698",
        "Longitude": "120.6937633"
    },
    {
        "編號": "44",
        "屬性": "私立",
        "機構名稱": "台中市私立德康老人長期照顧中心(養護型)",
        "負責人": "林桂連",
        "區域別": "東區",
        "地址": "401臺中市東區東勢里玉皇街63號3~5樓",
        "電話": "04-22154179",
        "收容對象": "養護",
        "核定收容人數": "49(含插2管24床)",
        "立案日期": "104.08",
        "Latitude": "24.1473999",
        "Longitude": "120.693661"
    },
    {
        "編號": "45",
        "屬性": "私立",
        "機構名稱": "臺中市私立敬馨老人長期照顧中心(養護型)",
        "負責人": "吳祐萱",
        "區域別": "東區",
        "地址": "401臺中市東區自由路三段314巷2號",
        "電話": "04-22116802",
        "收容對象": "養護",
        "核定收容人數": "49(含插2管24床)",
        "立案日期": "104.12",
        "Latitude": "24.142357",
        "Longitude": "120.69519"
    },
    {
        "編號": "46",
        "屬性": "私立",
        "機構名稱": "財團法人基督教福音信義傳道會附設台中市私立信義老人養護中心",
        "負責人": "尤寶珍",
        "區域別": "東勢區",
        "地址": "423臺中市東勢區泰昌里東崎路五段425號",
        "電話": "04-25888225",
        "收容對象": "養護",
        "核定收容人數": "49(含插2管11床)",
        "立案日期": "90.04",
        "Latitude": "24.2513102",
        "Longitude": "120.8320833"
    },
    {
        "編號": "47",
        "屬性": "私立",
        "機構名稱": "台中市私立至善園老人養護中心",
        "負責人": "黃信堯",
        "區域別": "南屯區",
        "地址": "408臺中市南屯區南屯里五福街205號",
        "電話": "04-23852299",
        "收容對象": "養護",
        "核定收容人數": "49(含插2管20床)",
        "立案日期": "95.05",
        "Latitude": "24.1396115",
        "Longitude": "120.6372872"
    },
    {
        "編號": "48",
        "屬性": "私立",
        "機構名稱": "台中市私立葳采老人長期照顧中心(養護型)",
        "負責人": "黃馨慧",
        "區域別": "南屯區",
        "地址": "408臺中市南屯區永春南路188巷71號",
        "電話": "04-23807788",
        "收容對象": "養護",
        "核定收容人數": "43(含插2管21床)",
        "立案日期": "100.11",
        "Latitude": "24.1383143",
        "Longitude": "120.6113579"
    },
    {
        "編號": "49",
        "屬性": "私立",
        "機構名稱": "財團法人臺中市私立永耕社會福利基金會附設臺中市私立永耕老人養護中心",
        "負責人": "林喬美",
        "區域別": "南區",
        "地址": "402臺中市南區樹義里文心南路766、768、770號",
        "電話": "04-22611698",
        "收容對象": "長照",
        "核定收容人數": "42",
        "立案日期": "92.1",
        "Latitude": "24.1127004",
        "Longitude": "120.6579743"
    },
    {
        "編號": "49",
        "屬性": "私立",
        "機構名稱": "財團法人臺中市私立永耕社會福利基金會附設臺中市私立永耕老人養護中心",
        "負責人": "林喬美",
        "區域別": "南區",
        "地址": "402臺中市南區樹義里文心南路766、768、770號",
        "電話": "04-22611698",
        "收容對象": "養護",
        "核定收容人數": "111",
        "立案日期": "92.1",
        "Latitude": "24.1127004",
        "Longitude": "120.6579743"
    },
    {
        "編號": "50",
        "屬性": "私立",
        "機構名稱": "台中市私立祥和老人養護中心",
        "負責人": "黃芬輕",
        "區域別": "南區",
        "地址": "402臺中市南區樹義里大慶街一段242號",
        "電話": "04-22605999",
        "收容對象": "養護",
        "核定收容人數": "45(含插2管13床)",
        "立案日期": "90.01",
        "Latitude": "24.113971",
        "Longitude": "120.655625"
    },
    {
        "編號": "51",
        "屬性": "私立",
        "機構名稱": "臺中市私立仁和老人養護中心",
        "負責人": "陳慧英",
        "區域別": "南區",
        "地址": "402臺中市南區長榮里愛國街55號2樓~5樓",
        "電話": "04-22261857",
        "收容對象": "養護",
        "核定收容人數": "40",
        "立案日期": "90.01",
        "Latitude": "24.1304739",
        "Longitude": "120.676546"
    },
    {
        "編號": "52",
        "屬性": "私立",
        "機構名稱": "臺中市私立享壽老人長期照顧中心(養護型)",
        "負責人": "蘇俊忠",
        "區域別": "烏日區",
        "地址": "414臺中市烏日區麻園東街76號",
        "電話": "04-23385355",
        "收容對象": "養護",
        "核定收容人數": "49(含插2管24床)",
        "立案日期": "105.1",
        "Latitude": "24.1048985",
        "Longitude": "120.6332125"
    },
    {
        "編號": "53",
        "屬性": "私立",
        "機構名稱": "台中市私立昇柏老人養護中心",
        "負責人": "陳惠娟",
        "區域別": "烏日區",
        "地址": "414臺中市烏日區學田里一鄰學田路732號",
        "電話": "04-23381438",
        "收容對象": "養護",
        "核定收容人數": "34(含插2管10床)",
        "立案日期": "93.11",
        "Latitude": "24.1256711",
        "Longitude": "120.6072654"
    },
    {
        "編號": "54",
        "屬性": "私立",
        "機構名稱": "臺中市私立泰安老人養護中心",
        "負責人": "陳品安",
        "區域別": "烏日區",
        "地址": "414臺中市烏日區九德里中山路一段548號8、9樓",
        "電話": "04-23380707",
        "收容對象": "養護",
        "核定收容人數": "49",
        "立案日期": "94.11",
        "Latitude": "24.1069325",
        "Longitude": "120.6348674"
    },
    {
        "編號": "55",
        "屬性": "私立",
        "機構名稱": "臺中市私立松群老人養護中心",
        "負責人": "王衍三",
        "區域別": "神岡區",
        "地址": "429臺中市神岡區圳前里神圳路82號",
        "電話": "04-25625627",
        "收容對象": "養護",
        "核定收容人數": "48(含插2管18床)",
        "立案日期": "91.09",
        "Latitude": "24.266202",
        "Longitude": "120.6589847"
    },
    {
        "編號": "56",
        "屬性": "私立",
        "機構名稱": "財團法人臺中市私立好耆老人長期照顧中心",
        "負責人": "王志財",
        "區域別": "梧棲區",
        "地址": "435臺中市梧棲區星美路197、199號",
        "電話": "04-26630197",
        "收容對象": "長照",
        "核定收容人數": "82",
        "立案日期": "105.07",
        "Latitude": "24.2541449",
        "Longitude": "120.5592287"
    },
    {
        "編號": "57",
        "屬性": "私立",
        "機構名稱": "臺中市私立育沛老人長期照顧中心(養護型)",
        "負責人": "鄭杰立",
        "區域別": "梧棲區",
        "地址": "435臺中市梧棲區草湳里21鄰自強三街96巷8號",
        "電話": "04-26392378",
        "收容對象": "養護",
        "核定收容人數": "26(含插2管13床)",
        "立案日期": "102.11",
        "Latitude": "24.242839",
        "Longitude": "120.5301524"
    },
    {
        "編號": "58",
        "屬性": "私立",
        "機構名稱": "臺中市私立孝親園老人養護中心",
        "負責人": "呂燦陽",
        "區域別": "潭子區",
        "地址": "427臺中市潭子區雅豐街197巷8號",
        "電話": "04-25345412",
        "收容對象": "養護",
        "核定收容人數": "42(含插2管21床)",
        "立案日期": "93.04",
        "Latitude": "24.2165069",
        "Longitude": "120.6932051"
    },
    {
        "編號": "59",
        "屬性": "私立",
        "機構名稱": "財團法人臺中市私立普濟社會福利慈善事業基金會附設臺中市私立普濟老人長期照顧中心(養護型)",
        "負責人": "吳惠群",
        "區域別": "龍井區",
        "地址": "434臺中市龍井區東海里遠東街209巷2號",
        "電話": "04-26522166",
        "收容對象": "養護",
        "核定收容人數": "46(含插2管23床)",
        "立案日期": "95.11",
        "Latitude": "24.1890373",
        "Longitude": "120.5974559"
    },
    {
        "編號": "60",
        "屬性": "私立",
        "機構名稱": "財團法人臺中市私立公老坪社會福利慈善事業基金會附設臺中市私立田園老人養護中心",
        "負責人": "陸桂森",
        "區域別": "豐原區",
        "地址": "420臺中市豐原區南嵩里水源路坪頂巷8-7號",
        "電話": "04-25220123",
        "收容對象": "養護",
        "核定收容人數": "200(含插2管25床)",
        "立案日期": "94.05",
        "Latitude": "24.2613317",
        "Longitude": "120.7578337"
    },
    {
        "編號": "61",
        "屬性": "私立",
        "機構名稱": "臺中市私立豐原長生老人養護中心",
        "負責人": "張良卿",
        "區域別": "豐原區",
        "地址": "420臺中市豐原區南村里水源路407號",
        "電話": "04-25151111",
        "收容對象": "養護",
        "核定收容人數": "49(含插2管20床)",
        "立案日期": "90.04",
        "Latitude": "24.255212",
        "Longitude": "120.733974"
    },
    {
        "編號": "62",
        "屬性": "私立",
        "機構名稱": "臺中市私立健安老人養護中心",
        "負責人": "鍾彬翊",
        "區域別": "豐原區",
        "地址": "420臺中市豐原區南田里南田街41號",
        "電話": "04-25255777",
        "收容對象": "養護",
        "核定收容人數": "49(含插2管22床)",
        "立案日期": "92.02",
        "Latitude": "24.2596384",
        "Longitude": "120.7369133"
    },
    {
        "編號": "63",
        "屬性": "私立",
        "機構名稱": "臺中市私立太夫老人養護中心",
        "負責人": "唐滿生",
        "區域別": "豐原區",
        "地址": "420臺中市豐原區東湳里角潭路二段119巷22號",
        "電話": "04-25232048",
        "收容對象": "養護",
        "核定收容人數": "20(含插2管10床)",
        "立案日期": "95.01",
        "Latitude": "24.2715093",
        "Longitude": "120.7293165"
    },
    {
        "編號": "64",
        "屬性": "私立",
        "機構名稱": "臺中市私立豐盛老人長期照顧中心",
        "負責人": "許淑琴",
        "區域別": "豐原區",
        "地址": "420臺中市豐原區南陽里圓環東路241號",
        "電話": "04-25122371",
        "收容對象": "長照",
        "核定收容人數": "23",
        "立案日期": "100.1",
        "Latitude": "24.2437626",
        "Longitude": "120.7219112"
    },
    {
        "編號": "65",
        "屬性": "私立",
        "機構名稱": "臺中市私立愛老郎老人長期照顧中心(養護型)",
        "負責人": "宋淑娟",
        "區域別": "豐原區",
        "地址": "420臺中市豐原區東湳里2鄰三豐路884巷69號",
        "電話": "04-25293499",
        "收容對象": "長照",
        "核定收容人數": "24",
        "立案日期": "102.04",
        "Latitude": "24.2755023",
        "Longitude": "120.72608"
    },
    {
        "編號": "65",
        "屬性": "私立",
        "機構名稱": "臺中市私立愛老郎老人長期照顧中心(養護型)",
        "負責人": "宋淑娟",
        "區域別": "豐原區",
        "地址": "420臺中市豐原區東湳里2鄰三豐路884巷69號",
        "電話": "04-25293499",
        "收容對象": "養護",
        "核定收容人數": "25",
        "立案日期": "102.04",
        "Latitude": "24.2755023",
        "Longitude": "120.72608"
    },
    {
        "編號": "66",
        "屬性": "私立",
        "機構名稱": "臺中市私立健民老人長期照顧中心(養護型)",
        "負責人": "黃至聖",
        "區域別": "霧峰區",
        "地址": "413臺中市霧峰區萬豐里中正路129號1樓",
        "電話": "04-23328287",
        "收容對象": "養護",
        "核定收容人數": "41(含插2管15床)",
        "立案日期": "104.12",
        "Latitude": "24.0223964",
        "Longitude": "120.696342"
    }
]